formulaic_ai/__init__.py
formulaic_ai/formulaic_ai.py
formulaic_ai-0.1.0.5.dist-info/METADATA
formulaic_ai-0.1.0.5.dist-info/WHEEL
formulaic_ai-0.1.0.5.dist-info/licenses/LICENSE
formulaic_ai-0.1.0.5.dist-info/RECORD
