Metadata-Version: 2.3
Name: formulaic-ai
Version: 0.1.0.5
Summary: The official Formulaic Python library
Project-URL: homepage, https:formulaic.app
Project-URL: repository, https://github.com/Mozilla-Ocho/formulaic-python
Project-URL: documentation, https://docs.formulaic.app
Author-email: Javaun Moradi <formulaic@mozilla.com>, Gabriel Habayeb <formulaic@mozilla.com>
License-Expression: Apache-2.0
License-File: LICENSE
Keywords: LLM,api,generative ai,language models,llama,mistral,openai,prompt engineering,prompt scripts
Classifier: Development Status :: 1 - Planning
Classifier: Intended Audience :: Developers
Classifier: License :: OSI Approved :: Apache Software License
Classifier: Operating System :: OS Independent
Classifier: Programming Language :: Python :: 3
Classifier: Programming Language :: Python :: 3.8
Classifier: Programming Language :: Python :: 3.9
Classifier: Programming Language :: Python :: 3.10
Classifier: Programming Language :: Python :: 3.11
Classifier: Programming Language :: Python :: 3.12
Classifier: Programming Language :: Python :: 3.13
Requires-Python: >=3.8
Requires-Dist: requests>=2.31.0
